gempaterkini/__init__.py
gempaterkini-0.0.1.dist-info/LICENSE
gempaterkini-0.0.1.dist-info/METADATA
gempaterkini-0.0.1.dist-info/WHEEL
gempaterkini-0.0.1.dist-info/top_level.txt
gempaterkini-0.0.1.dist-info/RECORD
