Metadata-Version: 2.1
Name: gempaterkini
Version: 0.0.1
Summary: A simple package to check latest earthquake in indonesia
Author-email: Joachim Nasution <joachimnasution@gmail.com>
License: GNU GENERAL PUBLIC LICENSE
Project-URL: Homepage, https://github.com/joachimnasution/gempaterkini
Classifier: Programming Language :: Python :: 3
Classifier: License :: OSI Approved :: GNU General Public License v3 (GPLv3)
Classifier: Operating System :: OS Independent
Requires-Python: >=3.7
License-File: LICENSE
